expressvpn/__init__.py
expressvpn/commands.py
expressvpn/wrapper.py
expressvpn_python-1.2.dist-info/LICENSE
expressvpn_python-1.2.dist-info/METADATA
expressvpn_python-1.2.dist-info/WHEEL
expressvpn_python-1.2.dist-info/top_level.txt
expressvpn_python-1.2.dist-info/RECORD
